README.rst
setup.py
jimmy/__init__.py
jimmy/jimmyctl.py
jimmy.egg-info/PKG-INFO
jimmy.egg-info/SOURCES.txt
jimmy.egg-info/dependency_links.txt
jimmy.egg-info/entry_points.txt
jimmy.egg-info/not-zip-safe
jimmy.egg-info/requires.txt
jimmy.egg-info/top_level.txt
jimmy/lib/__init__.py
jimmy/lib/api.py
jimmy/lib/common.py
jimmy/lib/core.py
jimmy/lib/schema.yaml
jimmy/modules/__init__.py
jimmy/modules/read_source.py
jimmy/modules/artifactory/__init__.py
jimmy/modules/artifactory/impl.py
jimmy/modules/artifactory/resources/jenkins.groovy
jimmy/modules/artifactory/resources/schema.yaml
jimmy/modules/artifactory/tests/__init__.py
jimmy/modules/artifactory/tests/test_artifactory.py
jimmy/modules/credentials/__init__.py
jimmy/modules/credentials/impl.py
jimmy/modules/credentials/resources/jenkins.groovy
jimmy/modules/credentials/resources/kubernetes.groovy
jimmy/modules/credentials/resources/schema.yaml
jimmy/modules/credentials/tests/__init__.py
jimmy/modules/credentials/tests/test_credentials.py
jimmy/modules/gearman/__init__.py
jimmy/modules/gearman/impl.py
jimmy/modules/gearman/resources/jenkins.groovy
jimmy/modules/gearman/resources/schema.yaml
jimmy/modules/gearman/tests/__init__.py
jimmy/modules/gearman/tests/test_gearman.py
jimmy/modules/gerrit/__init__.py
jimmy/modules/gerrit/impl.py
jimmy/modules/gerrit/resources/jenkins.groovy
jimmy/modules/gerrit/resources/schema.yaml
jimmy/modules/gerrit/tests/__init__.py
jimmy/modules/gerrit/tests/test_gerrit.py
jimmy/modules/git/__init__.py
jimmy/modules/git/impl.py
jimmy/modules/git/resources/jenkins.groovy
jimmy/modules/git/resources/schema.yaml
jimmy/modules/git/tests/__init__.py
jimmy/modules/git/tests/test_git.py
jimmy/modules/http_request/__init__.py
jimmy/modules/http_request/impl.py
jimmy/modules/http_request/resources/jenkins.groovy
jimmy/modules/http_request/resources/schema.yaml
jimmy/modules/http_request/tests/__init__.py
jimmy/modules/http_request/tests/test_http_requests.py
jimmy/modules/jenkins_configuration/__init__.py
jimmy/modules/jenkins_configuration/impl.py
jimmy/modules/jenkins_configuration/resources/jenkins.groovy
jimmy/modules/jenkins_configuration/resources/schema.yaml
