Metadata-Version: 1.1
Name: jimmy
Version: 0.2.11
Summary: Update jenkins configuration using YAML
Home-page: https://github.com/ci-team/jimmy
Author: CI Team
Author-email: UNKNOWN
License: ['Apache License 2.0']
Download-URL: https://github.com/ci-team/jimmy
Platform: Unix
Classifier: Development Status :: 5 - Production/Stable
Classifier: License :: OSI Approved :: Apache Software License
Classifier: Operating System :: Unix
Classifier: Programming Language :: Python :: 2.7
